[{"createdAt":"2026-05-26T16:57:45Z","description":"The object spine for TRUTHFRAMER: replayable visual truth frames for market reality.","isPrivate":false,"name":"truthframer-platform","nameWithOwner":"TRUTHFRAMER/truthframer-platform","primaryLanguage":{"name":"JavaScript"},"repositoryTopics":null,"updatedAt":"2026-06-02T06:06:24Z","url":"https://github.com/TRUTHFRAMER/truthframer-platform","visibility":"PUBLIC"},{"createdAt":"2026-05-26T17:01:48Z","description":"Public organization profile for TRUTHFRAMER.","isPrivate":false,"name":".github","nameWithOwner":"TRUTHFRAMER/.github","primaryLanguage":null,"repositoryTopics":null,"updatedAt":"2026-05-26T17:04:00Z","url":"https://github.com/TRUTHFRAMER/.github","visibility":"PUBLIC"}]
